zkstats/__init__.py
zkstats/cli.py
zkstats/computation.py
zkstats/core.py
zkstats/ops.py
zkstats-0.1.11.dist-info/METADATA
zkstats-0.1.11.dist-info/WHEEL
zkstats-0.1.11.dist-info/entry_points.txt
zkstats-0.1.11.dist-info/RECORD
