Metadata-Version: 2.1
Name: zkstats
Version: 0.1.11
Summary: 
Author: Jern Kunpittaya
Requires-Python: >=3.9,<4.0
Classifier: Programming Language :: Python :: 3
Classifier: Programming Language :: Python :: 3.9
Classifier: Programming Language :: Python :: 3.10
Classifier: Programming Language :: Python :: 3.11
Classifier: Programming Language :: Python :: 3.12
Requires-Dist: click (>=8.1.7,<9.0.0)
Requires-Dist: ezkl (==9.1.0)
Requires-Dist: matplotlib (>=3.8.2,<4.0.0)
Requires-Dist: numpy (>=1.26.2,<2.0.0)
Requires-Dist: onnx (>=1.15.0,<2.0.0)
Requires-Dist: requests (>=2.31.0,<3.0.0)
Requires-Dist: scipy (>=1.11.4,<2.0.0)
Requires-Dist: statistics (>=1.0.3,<2.0.0)
Requires-Dist: torch (==2.2.0)
